lab-09/lab-09.srcs/sources_1/new/ALUControl.v
// =============================================================================
// Module      : ALUControl
// Description : RISC-V ALU control unit.  Combines the 2-bit ALUOp signal
//               from MainControl with the funct3 and funct7 fields (and the
//               opcode for R-type SUB disambiguation) to produce a 4-bit
//               ALU operation code.
//
//               ALUOp encoding:
//               ?????????????????????????????????????????????????????????????
//               ? ALUOp  ? Instruction class                                ?
//               ?????????????????????????????????????????????????????????????
//               ?  2'b00 ? Load / Store  ? always ADD (address calc)        ?
//               ?  2'b01 ? Branch (BEQ)  ? always SUB (zero-flag compare)   ?
//               ?  2'b10 ? R-type / I-type ALU ? decoded via funct3 / funct7?
//               ?????????????????????????????????????????????????????????????
//
//               ALUControl 4-bit encoding:
//               ????????????????????????????????????????????????
//               ? 4'b0000  ? AND                               ?
//               ? 4'b0001  ? OR                                ?
//               ? 4'b0010  ? ADD                               ?
//               ? 4'b0011  ? XOR                               ?
//               ? 4'b0100  ? SLL (shift left logical)          ?
//               ? 4'b0101  ? SRL (shift right logical)         ?
//               ? 4'b0110  ? SUB                               ?
//               ????????????????????????????????????????????????
// =============================================================================

`timescale 1ns / 1ps

module ALUControl (
    input  [6:0] opcode,        // Full opcode - needed to distinguish SUB vs ADD
    input  [1:0] ALUOp,         // 2-bit selector from MainControl
    input  [2:0] funct3,        // funct3 field from the instruction word
    input  [6:0] funct7,        // funct7 field from the instruction word
    output reg [3:0] ALUControl // 4-bit ALU operation code sent to the ALU
);

    // -------------------------------------------------------------------------
    // Combinational decode block
    // -------------------------------------------------------------------------
    always @(*) begin

        // Default: ADD (safe fallback for any unrecognised combination)
        ALUControl = 4'b0010;

        case (ALUOp)

            // -----------------------------------------------------------------
            // ALUOp = 00 - Load / Store instructions
            //   The ALU only needs to compute  base + offset,  so always ADD.
            // -----------------------------------------------------------------
            2'b00: begin
                ALUControl = 4'b0010;   // ADD ? effective address calculation
            end

            // -----------------------------------------------------------------
            // ALUOp = 01 - Branch instructions (BEQ)
            //   The ALU subtracts rs1 - rs2 and the zero flag decides the branch.
            // -----------------------------------------------------------------
            2'b01: begin
                ALUControl = 4'b0110;   // SUB ? drives zero flag for BEQ
            end

            // -----------------------------------------------------------------
            // ALUOp = 10 - R-type and I-type ALU instructions
            //   funct3 selects the operation; for funct3=000 the funct7 bit
            //   distinguishes ADD/ADDI from SUB (R-type only).
            // -----------------------------------------------------------------
            2'b10: begin
                case (funct3)

                    // funct3 = 000 : ADD, ADDI, or SUB
                    3'b000: begin
                        // SUB only exists in R-type (opcode 0110011) and is
                        // identified by funct7[5] = 1  (full funct7 = 0100000).
                        if (opcode == 7'b0110011 && funct7 == 7'b0100000)
                            ALUControl = 4'b0110;   // SUB
                        else
                            ALUControl = 4'b0010;   // ADD / ADDI
                    end

                    // funct3 = 001 : SLL - Shift Left Logical
                    3'b001: ALUControl = 4'b0100;

                    // funct3 = 010 : SLT - Set Less Than
                    //   Not fully implemented; mapped to ADD as placeholder.
                    3'b010: ALUControl = 4'b0010;

                    // funct3 = 011 : SLTU - Set Less Than Unsigned
                    //   Not fully implemented; mapped to ADD as placeholder.
                    3'b011: ALUControl = 4'b0010;

                    // funct3 = 100 : XOR
                    3'b100: ALUControl = 4'b0011;

                    // funct3 = 101 : SRL - Shift Right Logical
                    3'b101: ALUControl = 4'b0101;

                    // funct3 = 110 : OR
                    3'b110: ALUControl = 4'b0001;

                    // funct3 = 111 : AND
                    3'b111: ALUControl = 4'b0000;

                    // Catch-all: default to ADD
                    default: ALUControl = 4'b0010;

                endcase
            end

            // -----------------------------------------------------------------
            // Default: unrecognised ALUOp ? ADD (safe fallback)
            // -----------------------------------------------------------------
            default: ALUControl = 4'b0010;

        endcase
    end

endmodule

lab-09/lab-09.srcs/sources_1/new/MainControl.v
// =============================================================================
// Module      : MainControl
// Description : RISC-V main control unit.  Decodes the 7-bit instruction
//               opcode and asserts the appropriate datapath control signals
//               for the five instruction classes supported:
//
//               Opcode        Class          Signals driven
//               ?????????????????????????????????????????????????????????????
//               0110011       R-type         RegWrite, ALUOp=10, ALUSrc=0
//               0010011       I-type (ALU)   RegWrite, ALUOp=10, ALUSrc=1
//               0000011       Load           RegWrite, MemRead, ALUSrc=1,
//                                            MemtoReg, ALUOp=00
//               0100011       Store          MemWrite, ALUSrc=1, ALUOp=00
//               1100011       Branch (BEQ)   Branch, ALUOp=01
//
// Outputs default to 0 for any unsupported opcode.
// =============================================================================

`timescale 1ns / 1ps

module MainControl (
    input  [6:0] opcode,        // 7-bit opcode field from the instruction

    // --- Datapath control outputs -------------------------------------------
    output reg        RegWrite, // 1 ? write result back to register file
    output reg [1:0]  ALUOp,    // ALU operation selector for ALUControl unit
    output reg        MemRead,  // 1 ? enable data-memory read
    output reg        MemWrite, // 1 ? enable data-memory write
    output reg        ALUSrc,   // 0 ? ALU src B = register; 1 ? immediate
    output reg        MemtoReg, // 0 ? WB data = ALU result; 1 ? memory data
    output reg        Branch    // 1 ? this is a branch instruction
);

    // -------------------------------------------------------------------------
    // Combinational decode block
    // All outputs are set to safe defaults at the top of every evaluation
    // so that partial case matches never leave outputs undefined.
    // -------------------------------------------------------------------------
    always @(*) begin

        // --- Safe / idle defaults --------------------------------------------
        RegWrite = 1'b0;
        ALUOp    = 2'b00;
        MemRead  = 1'b0;
        MemWrite = 1'b0;
        ALUSrc   = 1'b0;
        MemtoReg = 1'b0;
        Branch   = 1'b0;

        case (opcode)

            // -----------------------------------------------------------------
            // R-type instructions: ADD, SUB, SLL, SRL, AND, OR, XOR
            //   funct3 / funct7 further decoded inside ALUControl
            // -----------------------------------------------------------------
            7'b0110011: begin
                RegWrite = 1'b1;    // Result written to rd
                ALUOp    = 2'b10;   // ALUControl will use funct3/funct7
                ALUSrc   = 1'b0;    // Second ALU operand from register file
                MemtoReg = 1'b0;    // Write-back from ALU, not memory
            end

            // -----------------------------------------------------------------
            // I-type ALU instructions: ADDI (and other immediate ALU ops)
            //   Immediate is sign-extended and fed to ALU src B
            // -----------------------------------------------------------------
            7'b0010011: begin
                RegWrite = 1'b1;    // Result written to rd
                ALUOp    = 2'b10;   // ALUControl will use funct3
                ALUSrc   = 1'b1;    // Second ALU operand from sign-ext imm
                MemtoReg = 1'b0;    // Write-back from ALU, not memory
            end

            // -----------------------------------------------------------------
            // Load instructions: LW, LH, LB
            //   ALU computes base + offset; result used as memory address
            // -----------------------------------------------------------------
            7'b0000011: begin
                RegWrite = 1'b1;    // Loaded value written to rd
                ALUOp    = 2'b00;   // ADD for effective-address calculation
                MemRead  = 1'b1;    // Enable data-memory read
                ALUSrc   = 1'b1;    // Offset immediate to ALU src B
                MemtoReg = 1'b1;    // Write-back from memory, not ALU
            end

            // -----------------------------------------------------------------
            // Store instructions: SW, SH, SB
            //   ALU computes base + offset; rs2 written to that address
            // -----------------------------------------------------------------
            7'b0100011: begin
                RegWrite = 1'b0;    // No register write for stores
                ALUOp    = 2'b00;   // ADD for effective-address calculation
                MemWrite = 1'b1;    // Enable data-memory write
                ALUSrc   = 1'b1;    // Offset immediate to ALU src B
            end

            // -----------------------------------------------------------------
            // Branch instructions: BEQ
            //   ALU subtracts rs1 - rs2; zero flag used to decide branch
            // -----------------------------------------------------------------
            7'b1100011: begin
                RegWrite = 1'b0;    // No register write for branches
                ALUOp    = 2'b01;   // ALUControl will output SUB (0110)
                Branch   = 1'b1;    // Signal the PC mux to consider branching
                ALUSrc   = 1'b0;    // Second ALU operand from register file
            end

            // -----------------------------------------------------------------
            // Default: unsupported opcode - all outputs remain at safe defaults
            // -----------------------------------------------------------------
            default: begin
                /* No action needed; defaults set above are already safe */
            end

        endcase
    end

endmodule

lab-09/lab-09.srcs/sim_1/new/control_tb.v
`timescale 1ns / 1ps

module control_tb;

    // =========================================================================
    // Stimulus registers
    // =========================================================================
    reg [6:0] opcode;   // 7-bit opcode field
    reg [2:0] funct3;   // 3-bit funct3 field
    reg [6:0] funct7;   // 7-bit funct7 field

    // =========================================================================
    // MainControl output wires
    // =========================================================================
    wire        RegWrite;
    wire [1:0]  ALUOp;
    wire        MemRead;
    wire        MemWrite;
    wire        ALUSrc;
    wire        MemtoReg;
    wire        Branch;

    // =========================================================================
    // ALUControl output wire
    // =========================================================================
    wire [3:0]  ALUControl;

    // =========================================================================
    // MainControl instantiation
    // =========================================================================
    MainControl mc (
        .opcode   (opcode),
        .RegWrite (RegWrite),
        .ALUOp    (ALUOp),
        .MemRead  (MemRead),
        .MemWrite (MemWrite),
        .ALUSrc   (ALUSrc),
        .MemtoReg (MemtoReg),
        .Branch   (Branch)
    );

    // =========================================================================
    // ALUControl instantiation
    // =========================================================================
    ALUControl alu_ctrl (
        .opcode     (opcode),
        .ALUOp      (ALUOp),
        .funct3     (funct3),
        .funct7     (funct7),
        .ALUControl (ALUControl)
    );

    // =========================================================================
    // Stimulus: apply inputs and display outputs
    // =========================================================================
    initial begin
        $dumpfile("control_tb.vcd");
        $dumpvars(0, control_tb);

        $display("Instr | opcode  funct3 funct7 | RegWrite ALUOp MemRead MemWrite ALUSrc MemtoReg Branch ALUControl");
        $display("-------------------------------------------------------------------------------");

        // R-type instructions
        opcode = 7'b0110011; funct3 = 3'b000; funct7 = 7'b0000000; #10;
        $display("ADD   | %b %b %b | %b %b %b %b %b %b %b %b", opcode, funct3, funct7, RegWrite, ALUOp, MemRead, MemWrite, ALUSrc, MemtoReg, Branch, ALUControl);

        opcode = 7'b0110011; funct3 = 3'b000; funct7 = 7'b0100000; #10;
        $display("SUB   | %b %b %b | %b %b %b %b %b %b %b %b", opcode, funct3, funct7, RegWrite, ALUOp, MemRead, MemWrite, ALUSrc, MemtoReg, Branch, ALUControl);

        opcode = 7'b0110011; funct3 = 3'b001; funct7 = 7'b0000000; #10;
        $display("SLL   | %b %b %b | %b %b %b %b %b %b %b %b", opcode, funct3, funct7, RegWrite, ALUOp, MemRead, MemWrite, ALUSrc, MemtoReg, Branch, ALUControl);

        opcode = 7'b0110011; funct3 = 3'b101; funct7 = 7'b0000000; #10;
        $display("SRL   | %b %b %b | %b %b %b %b %b %b %b %b", opcode, funct3, funct7, RegWrite, ALUOp, MemRead, MemWrite, ALUSrc, MemtoReg, Branch, ALUControl);

        opcode = 7'b0110011; funct3 = 3'b111; funct7 = 7'b0000000; #10;
        $display("AND   | %b %b %b | %b %b %b %b %b %b %b %b", opcode, funct3, funct7, RegWrite, ALUOp, MemRead, MemWrite, ALUSrc, MemtoReg, Branch, ALUControl);

        opcode = 7'b0110011; funct3 = 3'b110; funct7 = 7'b0000000; #10;
        $display("OR    | %b %b %b | %b %b %b %b %b %b %b %b", opcode, funct3, funct7, RegWrite, ALUOp, MemRead, MemWrite, ALUSrc, MemtoReg, Branch, ALUControl);

        opcode = 7'b0110011; funct3 = 3'b100; funct7 = 7'b0000000; #10;
        $display("XOR   | %b %b %b | %b %b %b %b %b %b %b %b", opcode, funct3, funct7, RegWrite, ALUOp, MemRead, MemWrite, ALUSrc, MemtoReg, Branch, ALUControl);

        // I-type
        opcode = 7'b0010011; funct3 = 3'b000; funct7 = 7'b0000000; #10;
        $display("ADDI  | %b %b %b | %b %b %b %b %b %b %b %b", opcode, funct3, funct7, RegWrite, ALUOp, MemRead, MemWrite, ALUSrc, MemtoReg, Branch, ALUControl);

        // LOAD
        opcode = 7'b0000011; funct3 = 3'b010; funct7 = 7'b0000000; #10;
        $display("LW    | %b %b %b | %b %b %b %b %b %b %b %b", opcode, funct3, funct7, RegWrite, ALUOp, MemRead, MemWrite, ALUSrc, MemtoReg, Branch, ALUControl);

        opcode = 7'b0000011; funct3 = 3'b001; funct7 = 7'b0000000; #10;
        $display("LH    | %b %b %b | %b %b %b %b %b %b %b %b", opcode, funct3, funct7, RegWrite, ALUOp, MemRead, MemWrite, ALUSrc, MemtoReg, Branch, ALUControl);

        opcode = 7'b0000011; funct3 = 3'b000; funct7 = 7'b0000000; #10;
        $display("LB    | %b %b %b | %b %b %b %b %b %b %b %b", opcode, funct3, funct7, RegWrite, ALUOp, MemRead, MemWrite, ALUSrc, MemtoReg, Branch, ALUControl);

        // STORE
        opcode = 7'b0100011; funct3 = 3'b010; funct7 = 7'b0000000; #10;
        $display("SW    | %b %b %b | %b %b %b %b %b %b %b %b", opcode, funct3, funct7, RegWrite, ALUOp, MemRead, MemWrite, ALUSrc, MemtoReg, Branch, ALUControl);

        opcode = 7'b0100011; funct3 = 3'b001; funct7 = 7'b0000000; #10;
        $display("SH    | %b %b %b | %b %b %b %b %b %b %b %b", opcode, funct3, funct7, RegWrite, ALUOp, MemRead, MemWrite, ALUSrc, MemtoReg, Branch, ALUControl);

        opcode = 7'b0100011; funct3 = 3'b000; funct7 = 7'b0000000; #10;
        $display("SB    | %b %b %b | %b %b %b %b %b %b %b %b", opcode, funct3, funct7, RegWrite, ALUOp, MemRead, MemWrite, ALUSrc, MemtoReg, Branch, ALUControl);

        // BRANCH
        opcode = 7'b1100011; funct3 = 3'b000; funct7 = 7'b0000000; #10;
        $display("BEQ   | %b %b %b | %b %b %b %b %b %b %b %b", opcode, funct3, funct7, RegWrite, ALUOp, MemRead, MemWrite, ALUSrc, MemtoReg, Branch, ALUControl);

        // UNKNOWN opcode (default case)
        opcode = 7'b1111111; funct3 = 3'b000; funct7 = 7'b0000000; #10;
        $display("UNK   | %b %b %b | %b %b %b %b %b %b %b %b", opcode, funct3, funct7, RegWrite, ALUOp, MemRead, MemWrite, ALUSrc, MemtoReg, Branch, ALUControl);

        $finish;
    end

endmodule

lab-09/lab-09.sim/sim_1/behav/xsim/control_tb.vcd
$date
   Wed Mar 25 00:17:18 2026
$end
$version
  2020.1
$end
$timescale
  1ps
$end
$scope module control_tb $end
$var reg 7 ! opcode [6:0] $end
$var reg 3 " funct3 [2:0] $end
$var reg 7 # funct7 [6:0] $end
$var wire 1 $ RegWrite $end
$var wire 2 % ALUOp [1:0] $end
$var wire 1 & MemRead $end
$var wire 1 ' MemWrite $end
$var wire 1 ( ALUSrc $end
$var wire 1 ) MemtoReg $end
$var wire 1 * Branch $end
$var wire 4 + ALUControl [3:0] $end
$scope module mc $end
$var wire 7 , opcode [6:0] $end
$var reg 1 - RegWrite $end
$var reg 2 . ALUOp [1:0] $end
$var reg 1 / MemRead $end
$var reg 1 0 MemWrite $end
$var reg 1 1 ALUSrc $end
$var reg 1 2 MemtoReg $end
$var reg 1 3 Branch $end
$upscope $end
$scope module alu_ctrl $end
$var wire 7 4 opcode [6:0] $end
$var wire 2 % ALUOp [1:0] $end
$var wire 3 5 funct3 [2:0] $end
$var wire 7 6 funct7 [6:0] $end
$var reg 4 7 ALUControl [3:0] $end
$upscope $end
$upscope $end
$enddefinitions $end
#0
$dumpvars
b110011 !
b0 "
b0 #
1$
b10 %
0&
0'
0(
0)
0*
b10 +
b110011 ,
1-
b10 .
0/
00
01
02
03
b110011 4
b0 5
b0 6
b10 7
$end
#10000
b110011 !
b0 "
b100000 #
b110 +
b100000 6
b110 7
#20000
b110011 !
b1 "
b0 #
b100 +
b1 5
b0 6
b100 7
#30000
b110011 !
b101 "
b0 #
b101 +
b101 5
b101 7
#40000
b110011 !
b111 "
b0 #
b0 +
b111 5
b0 7
#50000
b110011 !
b110 "
b0 #
b1 +
b110 5
b1 7
#60000
b110011 !
b100 "
b0 #
b11 +
b100 5
b11 7
#70000
b10011 !
b0 "
b0 #
b10 %
1(
b10 +
b10011 ,
1-
b10 .
0/
00
11
02
03
b10011 4
b0 5
b10 7
#80000
b11 !
b10 "
b0 #
b0 %
1&
1)
b11 ,
1-
b0 .
1/
00
11
12
03
b11 4
b10 5
b10 7
#90000
b11 !
b1 "
b0 #
b1 5
b10 7
#100000
b11 !
b0 "
b0 #
b0 5
b10 7
#110000
b100011 !
b10 "
b0 #
0$
0&
1'
0)
b100011 ,
0-
b0 .
0/
10
11
02
03
b100011 4
b10 5
b10 7
#120000
b100011 !
b1 "
b0 #
b1 5
b10 7
#130000
b100011 !
b0 "
b0 #
b0 5
b10 7
#140000
b1100011 !
b0 "
b0 #
b1 %
0'
0(
1*
b110 +
b1100011 ,
0-
b1 .
0/
00
01
02
13
b1100011 4
b110 7
